duo_web/__init__.py
duo_web-1.3.1.data/data/js/Duo-Web-v2.js
duo_web-1.3.1.data/data/js/Duo-Web-v2.min.js
duo_web-1.3.1.dist-info/LICENSE
duo_web-1.3.1.dist-info/METADATA
duo_web-1.3.1.dist-info/WHEEL
duo_web-1.3.1.dist-info/top_level.txt
duo_web-1.3.1.dist-info/RECORD
